<?xml version="1.0" encoding="UTF-8"?>
<root>
  <hmm_emission_distribution_0>0
1
0
0
0
0
</hmm_emission_distribution_0>
  <hmm_emission_distribution_1>0
0
1
0
0
0
</hmm_emission_distribution_1>
  <hmm_emission_distribution_2>0
0
0.428571428571429
0.333333333333333
0.142857142857143
0.0952380952380952
</hmm_emission_distribution_2>
  <hmm_emission_distribution_3>0.0333333333333333
0.0333333333333333
0.166666666666667
0.433333333333333
0.3
0.0333333333333333
</hmm_emission_distribution_3>
  <hmm_emission_distribution_4>0
0
0.238095238095238
0.380952380952381
0.285714285714286
0.0952380952380952
</hmm_emission_distribution_4>
  <hmm_emission_distribution_5>0
0
0
0.333333333333333
0.5
0.166666666666667
</hmm_emission_distribution_5>
  <hmm_states>6</hmm_states>
  <hmm_transition>0,0.5,0,0,0,0
0,0,0.0952380952380952,0,0,0
0,0,0.428571428571429,0.241379310344828,0.142857142857143,0.333333333333333
1,0.5,0.238095238095238,0.448275862068966,0.428571428571429,0.166666666666667
0,0,0.238095238095238,0.241379310344828,0.285714285714286,0.333333333333333
0,0,0,0.0689655172413793,0.142857142857143,0.166666666666667
</hmm_transition>
  <hmm_type>discrete</hmm_type>
</root>
