<?xml version="1.0" encoding="UTF-8"?>
<root>
  <hmm_emission_distribution_0>0
0.285714285714286
0.571428571428571
0.142857142857143
0
0
</hmm_emission_distribution_0>
  <hmm_emission_distribution_1>0.0526315789473684
0.263157894736842
0.263157894736842
0.368421052631579
0.0526315789473684
0
</hmm_emission_distribution_1>
  <hmm_emission_distribution_2>0.148148148148148
0.222222222222222
0.333333333333333
0.296296296296296
0
0
</hmm_emission_distribution_2>
  <hmm_emission_distribution_3>0.142857142857143
0.285714285714286
0.285714285714286
0.19047619047619
0.0952380952380952
0
</hmm_emission_distribution_3>
  <hmm_emission_distribution_4>0
0
0.333333333333333
0.166666666666667
0.333333333333333
0.166666666666667
</hmm_emission_distribution_4>
  <hmm_emission_distribution_5>0
0
1
0
0
0
</hmm_emission_distribution_5>
  <hmm_states>6</hmm_states>
  <hmm_transition>0,0.105263157894737,0.148148148148148,0.0476190476190476,0,0
0.142857142857143,0.263157894736842,0.185185185185185,0.333333333333333,0.2,0
0.428571428571429,0.315789473684211,0.333333333333333,0.380952380952381,0,0
0.428571428571429,0.315789473684211,0.222222222222222,0.19047619047619,0.4,0
0,0,0.0740740740740741,0.0476190476190476,0.4,1
0,0,0.037037037037037,0,0,0
</hmm_transition>
  <hmm_type>discrete</hmm_type>
</root>
