<?xml version="1.0" encoding="UTF-8"?>
<root>
  <hmm_emission_distribution_0>0
0.666666666666667
0.333333333333333
0
0
0
0
</hmm_emission_distribution_0>
  <hmm_emission_distribution_1>0.0434782608695652
0.391304347826087
0.304347826086957
0.173913043478261
0.0434782608695652
0
0.0434782608695652
</hmm_emission_distribution_1>
  <hmm_emission_distribution_2>0.0555555555555556
0.444444444444444
0.0555555555555556
0.444444444444444
0
0
0
</hmm_emission_distribution_2>
  <hmm_emission_distribution_3>0
0.235294117647059
0.529411764705882
0.176470588235294
0.0588235294117647
0
0
</hmm_emission_distribution_3>
  <hmm_emission_distribution_4>0.5
0
0
0.5
0
0
0
</hmm_emission_distribution_4>
  <hmm_emission_distribution_5>0
0
0
0
0
0
0
</hmm_emission_distribution_5>
  <hmm_emission_distribution_6>0
0
0
1
0
0
0
</hmm_emission_distribution_6>
  <hmm_states>7</hmm_states>
  <hmm_transition>0,0.0909090909090909,0.0555555555555556,0,0,0,0
0.333333333333333,0.409090909090909,0.388888888888889,0.235294117647059,0.5,0,1
0.333333333333333,0.318181818181818,0.0555555555555556,0.470588235294118,0,0,0
0,0.181818181818182,0.5,0.176470588235294,0.5,0,0
0.333333333333333,0,0,0.0588235294117647,0,0,0
0,0,0,0,0,0,0
0,0,0,0.0588235294117647,0,0,0
</hmm_transition>
  <hmm_type>discrete</hmm_type>
</root>
